blockhouse/MarketClient.py
blockhouse/TradeClient.py
blockhouse/Transfer.py
blockhouse/__init__.py
blockhouse/client/__init__.py
blockhouse/client/exceptions.py
blockhouse/client/s3_connector.py
blockhouse/client/sor_connector.py
blockhouse-1.0.31.dist-info/licenses/LICENSE
blockhouse-1.0.31.dist-info/METADATA
blockhouse-1.0.31.dist-info/WHEEL
blockhouse-1.0.31.dist-info/top_level.txt
blockhouse-1.0.31.dist-info/RECORD
