Metadata-Version: 2.4
Name: blockhouse
Version: 1.0.31
Summary: Blockhouse SDK
Author: Blockhouse Labs
Author-email: <mail@blockhouse.com>
Keywords: python,blockhouse,sdk,stock,market,trading,algotrading,finance,financial,stocks,market,data,api,wrapper
Classifier: Development Status :: 5 - Production/Stable
Classifier: Intended Audience :: Developers
Classifier: Programming Language :: Python :: 3
Classifier: Operating System :: Unix
Classifier: Operating System :: MacOS :: MacOS X
Classifier: Operating System :: Microsoft :: Windows
Classifier: License :: OSI Approved :: MIT License
License-File: LICENSE
Requires-Dist: requests
Requires-Dist: boto3
Dynamic: author
Dynamic: author-email
Dynamic: classifier
Dynamic: description
Dynamic: description-content-type
Dynamic: keywords
Dynamic: license-file
Dynamic: requires-dist
Dynamic: summary
